simurgh/__init__.py
simurgh/actor.py
simurgh/photon.py
simurgh-0.0.5.dist-info/LICENSE
simurgh-0.0.5.dist-info/METADATA
simurgh-0.0.5.dist-info/WHEEL
simurgh-0.0.5.dist-info/top_level.txt
simurgh-0.0.5.dist-info/RECORD
